[
    { "id": "sc-1", "name": "Abdon Batista" },
    { "id": "sc-2", "name": "Abelardo Luz" },
    { "id": "sc-3", "name": "Agrolândia" },
    { "id": "sc-4", "name": "Agronômica" },
    { "id": "sc-5", "name": "Água Doce" },
    { "id": "sc-6", "name": "Águas de Chapecó" },
    { "id": "sc-7", "name": "Águas Frias" },
    { "id": "sc-8", "name": "Águas Mornas" },
    { "id": "sc-9", "name": "Alfredo Wagner" },
    { "id": "sc-10", "name": "Alto Bela Vista" },
    { "id": "sc-11", "name": "Anchieta" },
    { "id": "sc-12", "name": "Angelina" },
    { "id": "sc-13", "name": "Anita Garibaldi" },
    { "id": "sc-14", "name": "Anitápolis" },
    { "id": "sc-15", "name": "Antônio Carlos" },
    { "id": "sc-16", "name": "Apiúna" },
    { "id": "sc-17", "name": "Arabutã" },
    { "id": "sc-18", "name": "Araquari" },
    { "id": "sc-19", "name": "Araranguá" },
    { "id": "sc-20", "name": "Armazém" },
    { "id": "sc-21", "name": "Arroio Trinta" },
    { "id": "sc-22", "name": "Arvoredo" },
    { "id": "sc-23", "name": "Ascurra" },
    { "id": "sc-24", "name": "Atalanta" },
    { "id": "sc-25", "name": "Aurora" },
    { "id": "sc-26", "name": "Balneário Arroio do Silva" },
    { "id": "sc-27", "name": "Balneário Barra do Sul" },
    { "id": "sc-28", "name": "Balneário Camboriú" },
    { "id": "sc-29", "name": "Balneário Gaivota" },
    { "id": "sc-30", "name": "Balneário Piçarras" },
    { "id": "sc-31", "name": "Balneário Rincão" },
    { "id": "sc-32", "name": "Bandeirante" },
    { "id": "sc-33", "name": "Barra Bonita" },
    { "id": "sc-34", "name": "Barra Velha" },
    { "id": "sc-35", "name": "Bela Vista do Toldo" },
    { "id": "sc-36", "name": "Belmonte" },
    { "id": "sc-37", "name": "Benedito Novo" },
    { "id": "sc-38", "name": "Biguaçu" },
    { "id": "sc-39", "name": "Blumenau" },
    { "id": "sc-40", "name": "Bocaina do Sul" },
    { "id": "sc-41", "name": "Bom Jardim da Serra" },
    { "id": "sc-42", "name": "Bom Jesus" },
    { "id": "sc-43", "name": "Bom Jesus do Oeste" },
    { "id": "sc-44", "name": "Bom Retiro" },
    { "id": "sc-45", "name": "Bombinhas" },
    { "id": "sc-46", "name": "Botuverá" },
    { "id": "sc-47", "name": "Braço do Norte" },
    { "id": "sc-48", "name": "Braço do Trombudo" },
    { "id": "sc-49", "name": "Brunópolis" },
    { "id": "sc-50", "name": "Brusque" },
    { "id": "sc-51", "name": "Caçador" },
    { "id": "sc-52", "name": "Caibi" },
    { "id": "sc-53", "name": "Calmon" },
    { "id": "sc-54", "name": "Camboriú" },
    { "id": "sc-55", "name": "Campo Alegre" },
    { "id": "sc-56", "name": "Campo Belo do Sul" },
    { "id": "sc-57", "name": "Campo Erê" },
    { "id": "sc-58", "name": "Campos Novos" },
    { "id": "sc-59", "name": "Canelinha" },
    { "id": "sc-60", "name": "Canoinhas" },
    { "id": "sc-61", "name": "Capão Alto" },
    { "id": "sc-62", "name": "Capinzal" },
    { "id": "sc-63", "name": "Capivari de Baixo" },
    { "id": "sc-64", "name": "Catanduvas" },
    { "id": "sc-65", "name": "Caxambu do Sul" },
    { "id": "sc-66", "name": "Celso Ramos" },
    { "id": "sc-67", "name": "Cerro Negro" },
    { "id": "sc-68", "name": "Chapadão do Lageado" },
    { "id": "sc-69", "name": "Chapecó" },
    { "id": "sc-70", "name": "Cocal do Sul" },
    { "id": "sc-71", "name": "Concórdia" },
    { "id": "sc-72", "name": "Cordilheira Alta" },
    { "id": "sc-73", "name": "Coronel Freitas" },
    { "id": "sc-74", "name": "Coronel Martins" },
    { "id": "sc-75", "name": "Correia Pinto" },
    { "id": "sc-76", "name": "Corupá" },
    { "id": "sc-77", "name": "Criciúma" },
    { "id": "sc-78", "name": "Cunha Porã" },
    { "id": "sc-79", "name": "Cunhataí" },
    { "id": "sc-80", "name": "Curitibanos" },
    { "id": "sc-81", "name": "Descanso" },
    { "id": "sc-82", "name": "Dionísio Cerqueira" },
    { "id": "sc-83", "name": "Dona Emma" },
    { "id": "sc-84", "name": "Doutor Pedrinho" },
    { "id": "sc-85", "name": "Entre Rios" },
    { "id": "sc-86", "name": "Ermo" },
    { "id": "sc-87", "name": "Erval Velho" },
    { "id": "sc-88", "name": "Faxinal dos Guedes" },
    { "id": "sc-89", "name": "Flor do Sertão" },
    { "id": "sc-90", "name": "Florianópolis" },
    { "id": "sc-91", "name": "Formosa do Sul" },
    { "id": "sc-92", "name": "Forquilhinha" },
    { "id": "sc-93", "name": "Fraiburgo" },
    { "id": "sc-94", "name": "Frei Rogério" },
    { "id": "sc-95", "name": "Galvão" },
    { "id": "sc-96", "name": "Garopaba" },
    { "id": "sc-97", "name": "Garuva" },
    { "id": "sc-98", "name": "Gaspar" },
    { "id": "sc-99", "name": "Governador Celso Ramos" },
    { "id": "sc-100", "name": "Grão Pará" },
    { "id": "sc-101", "name": "Gravatal" },
    { "id": "sc-102", "name": "Guabiruba" },
    { "id": "sc-103", "name": "Guaraciaba" },
    { "id": "sc-104", "name": "Guaramirim" },
    { "id": "sc-105", "name": "Guarujá do Sul" },
    { "id": "sc-106", "name": "Guatambú" },
    { "id": "sc-107", "name": "Herval d'Oeste" },
    { "id": "sc-108", "name": "Ibiam" },
    { "id": "sc-109", "name": "Ibicaré" },
    { "id": "sc-110", "name": "Ibirama" },
    { "id": "sc-111", "name": "Içara" },
    { "id": "sc-112", "name": "Ilhota" },
    { "id": "sc-113", "name": "Imaruí" },
    { "id": "sc-114", "name": "Imbituba" },
    { "id": "sc-115", "name": "Imbuia" },
    { "id": "sc-116", "name": "Indaial" },
    { "id": "sc-117", "name": "Iomerê" },
    { "id": "sc-118", "name": "Ipira" },
    { "id": "sc-119", "name": "Iporã do Oeste" },
    { "id": "sc-120", "name": "Ipuaçu" },
    { "id": "sc-121", "name": "Ipumirim" },
    { "id": "sc-122", "name": "Iraceminha" },
    { "id": "sc-123", "name": "Irani" },
    { "id": "sc-124", "name": "Irati" },
    { "id": "sc-125", "name": "Irineópolis" },
    { "id": "sc-126", "name": "Itá" },
    { "id": "sc-127", "name": "Itaiópolis" },
    { "id": "sc-128", "name": "Itajaí" },
    { "id": "sc-129", "name": "Itapema" },
    { "id": "sc-130", "name": "Itapiranga" },
    { "id": "sc-131", "name": "Itapoá" },
    { "id": "sc-132", "name": "Ituporanga" },
    { "id": "sc-133", "name": "Jaborá" },
    { "id": "sc-134", "name": "Jacinto Machado" },
    { "id": "sc-135", "name": "Jaguaruna" },
    { "id": "sc-136", "name": "Jaraguá do Sul" },
    { "id": "sc-137", "name": "Jardinópolis" },
    { "id": "sc-138", "name": "Joaçaba" },
    { "id": "sc-139", "name": "Joinville" },
    { "id": "sc-140", "name": "José Boiteux" },
    { "id": "sc-141", "name": "Jupiá" },
    { "id": "sc-142", "name": "Lacerdópolis" },
    { "id": "sc-143", "name": "Lages" },
    { "id": "sc-144", "name": "Laguna" },
    { "id": "sc-145", "name": "Lajeado Grande" },
    { "id": "sc-146", "name": "Laurentino" },
    { "id": "sc-147", "name": "Lauro Muller" },
    { "id": "sc-148", "name": "Lebon Régis" },
    { "id": "sc-149", "name": "Leoberto Leal" },
    { "id": "sc-150", "name": "Lindóia do Sul" },
    { "id": "sc-151", "name": "Lontras" },
    { "id": "sc-152", "name": "Luiz Alves" },
    { "id": "sc-153", "name": "Luzerna" },
    { "id": "sc-154", "name": "Macieira" },
    { "id": "sc-155", "name": "Mafra" },
    { "id": "sc-156", "name": "Major Gercino" },
    { "id": "sc-157", "name": "Major Vieira" },
    { "id": "sc-158", "name": "Maracajá" },
    { "id": "sc-159", "name": "Maravilha" },
    { "id": "sc-160", "name": "Marema" },
    { "id": "sc-161", "name": "Massaranduba" },
    { "id": "sc-162", "name": "Matos Costa" },
    { "id": "sc-163", "name": "Meleiro" },
    { "id": "sc-164", "name": "Mirim Doce" },
    { "id": "sc-165", "name": "Modelo" },
    { "id": "sc-166", "name": "Mondaí" },
    { "id": "sc-167", "name": "Monte Carlo" },
    { "id": "sc-168", "name": "Monte Castelo" },
    { "id": "sc-169", "name": "Morro da Fumaça" },
    { "id": "sc-170", "name": "Morro Grande" },
    { "id": "sc-171", "name": "Navegantes" },
    { "id": "sc-172", "name": "Nova Erechim" },
    { "id": "sc-173", "name": "Nova Itaberaba" },
    { "id": "sc-174", "name": "Nova Trento" },
    { "id": "sc-175", "name": "Nova Veneza" },
    { "id": "sc-176", "name": "Novo Horizonte" },
    { "id": "sc-177", "name": "Orleans" },
    { "id": "sc-178", "name": "Otacílio Costa" },
    { "id": "sc-179", "name": "Ouro" },
    { "id": "sc-180", "name": "Ouro Verde" },
    { "id": "sc-181", "name": "Paial" },
    { "id": "sc-182", "name": "Painel" },
    { "id": "sc-183", "name": "Palhoça" },
    { "id": "sc-184", "name": "Palma Sola" },
    { "id": "sc-185", "name": "Palmeira" },
    { "id": "sc-186", "name": "Palmitos" },
    { "id": "sc-187", "name": "Papanduva" },
    { "id": "sc-188", "name": "Paraíso" },
    { "id": "sc-189", "name": "Passo de Torres" },
    { "id": "sc-190", "name": "Passos Maia" },
    { "id": "sc-191", "name": "Paulo Lopes" },
    { "id": "sc-192", "name": "Pedras Grandes" },
    { "id": "sc-193", "name": "Penha" },
    { "id": "sc-194", "name": "Peritiba" },
    { "id": "sc-195", "name": "Petrolândia" },
    { "id": "sc-196", "name": "Pinhalzinho" },
    { "id": "sc-197", "name": "Pinheiro Preto" },
    { "id": "sc-198", "name": "Piratuba" },
    { "id": "sc-199", "name": "Planalto Alegre" },
    { "id": "sc-200", "name": "Pomerode" },
    { "id": "sc-201", "name": "Ponte Alta" },
    { "id": "sc-202", "name": "Ponte Alta do Norte" },
    { "id": "sc-203", "name": "Ponte Serrada" },
    { "id": "sc-204", "name": "Porto Belo" },
    { "id": "sc-205", "name": "Porto União" },
    { "id": "sc-206", "name": "Pouso Redondo" },
    { "id": "sc-207", "name": "Praia Grande" },
    { "id": "sc-208", "name": "Presidente Castello Branco" },
    { "id": "sc-209", "name": "Presidente Getúlio" },
    { "id": "sc-210", "name": "Presidente Nereu" },
    { "id": "sc-211", "name": "Princesa" },
    { "id": "sc-212", "name": "Quilombo" },
    { "id": "sc-213", "name": "Rancho Queimado" },
    { "id": "sc-214", "name": "Rio das Antas" },
    { "id": "sc-215", "name": "Rio do Campo" },
    { "id": "sc-216", "name": "Rio do Oeste" },
    { "id": "sc-217", "name": "Rio do Sul" },
    { "id": "sc-218", "name": "Rio dos Cedros" },
    { "id": "sc-219", "name": "Rio Fortuna" },
    { "id": "sc-220", "name": "Rio Negrinho" },
    { "id": "sc-221", "name": "Rio Rufino" },
    { "id": "sc-222", "name": "Riqueza" },
    { "id": "sc-223", "name": "Rodeio" },
    { "id": "sc-224", "name": "Romelândia" },
    { "id": "sc-225", "name": "Salete" },
    { "id": "sc-226", "name": "Saltinho" },
    { "id": "sc-227", "name": "Salto Veloso" },
    { "id": "sc-228", "name": "Sangão" },
    { "id": "sc-229", "name": "Santa Cecília" },
    { "id": "sc-230", "name": "Santa Helena" },
    { "id": "sc-231", "name": "Santa Rosa de Lima" },
    { "id": "sc-232", "name": "Santa Rosa do Sul" },
    { "id": "sc-233", "name": "Santa Terezinha" },
    { "id": "sc-234", "name": "Santa Terezinha do Progresso" },
    { "id": "sc-235", "name": "Santiago do Sul" },
    { "id": "sc-236", "name": "Santo Amaro da Imperatriz" },
    { "id": "sc-237", "name": "São Bento do Sul" },
    { "id": "sc-238", "name": "São Bernardino" },
    { "id": "sc-239", "name": "São Bonifácio" },
    { "id": "sc-240", "name": "São Carlos" },
    { "id": "sc-241", "name": "São Cristóvão do Sul" },
    { "id": "sc-242", "name": "São Domingos" },
    { "id": "sc-243", "name": "São Francisco do Sul" },
    { "id": "sc-244", "name": "São João Batista" },
    { "id": "sc-245", "name": "São João do Itaperiú" },
    { "id": "sc-246", "name": "São João do Oeste" },
    { "id": "sc-247", "name": "São João do Sul" },
    { "id": "sc-248", "name": "São Joaquim" },
    { "id": "sc-249", "name": "São José" },
    { "id": "sc-250", "name": "São José do Cedro" },
    { "id": "sc-251", "name": "São José do Cerrito" },
    { "id": "sc-252", "name": "São Lourenço do Oeste" },
    { "id": "sc-253", "name": "São Ludgero" },
    { "id": "sc-254", "name": "São Martinho" },
    { "id": "sc-255", "name": "São Miguel da Boa Vista" },
    { "id": "sc-256", "name": "São Miguel do Oeste" },
    { "id": "sc-257", "name": "São Pedro de Alcântara" },
    { "id": "sc-258", "name": "Saudades" },
    { "id": "sc-259", "name": "Schroeder" },
    { "id": "sc-260", "name": "Seara" },
    { "id": "sc-261", "name": "Serra Alta" },
    { "id": "sc-262", "name": "Siderópolis" },
    { "id": "sc-263", "name": "Sombrio" },
    { "id": "sc-264", "name": "Sul Brasil" },
    { "id": "sc-265", "name": "Taió" },
    { "id": "sc-266", "name": "Tangará" },
    { "id": "sc-267", "name": "Tigrinhos" },
    { "id": "sc-268", "name": "Tijucas" },
    { "id": "sc-269", "name": "Timbé do Sul" },
    { "id": "sc-270", "name": "Timbó" },
    { "id": "sc-271", "name": "Timbó Grande" },
    { "id": "sc-272", "name": "Três Barras" },
    { "id": "sc-273", "name": "Treviso" },
    { "id": "sc-274", "name": "Treze de Maio" },
    { "id": "sc-275", "name": "Treze Tílias" },
    { "id": "sc-276", "name": "Trombudo Central" },
    { "id": "sc-277", "name": "Tubarão" },
    { "id": "sc-278", "name": "Tunápolis" },
    { "id": "sc-279", "name": "Turvo" },
    { "id": "sc-280", "name": "União do Oeste" },
    { "id": "sc-281", "name": "Urubici" },
    { "id": "sc-282", "name": "Urupema" },
    { "id": "sc-283", "name": "Urussanga" },
    { "id": "sc-284", "name": "Vargeão" },
    { "id": "sc-285", "name": "Vargem" },
    { "id": "sc-286", "name": "Vargem Bonita" },
    { "id": "sc-287", "name": "Vidal Ramos" },
    { "id": "sc-288", "name": "Videira" },
    { "id": "sc-289", "name": "Vitor Meireles" },
    { "id": "sc-290", "name": "Witmarsum" },
    { "id": "sc-291", "name": "Xanxerê" },
    { "id": "sc-292", "name": "Xavantina" },
    { "id": "sc-293", "name": "Xaxim" },
    { "id": "sc-294", "name": "Zortéa" }
]